setup.py
ayushabg_distributions/Binomialdistribution.py
ayushabg_distributions/Gaussiandistribution.py
ayushabg_distributions/Generaldistribution.py
ayushabg_distributions/__init__.py
ayushabg_distributions.egg-info/PKG-INFO
ayushabg_distributions.egg-info/SOURCES.txt
ayushabg_distributions.egg-info/dependency_links.txt
ayushabg_distributions.egg-info/not-zip-safe
ayushabg_distributions.egg-info/top_level.txt