Metadata-Version: 1.0
Name: ayushabg-distributions
Version: 0.1
Summary: Gaussian distributions
Home-page: UNKNOWN
Author: Ayush Gupta
Author-email: ayushabg@gmail.com
License: UNKNOWN
Platform: UNKNOWN
